src/__init__.py
src/cli.py
src/config.py
src/logging.py
src/models.py
src/adapters/__init__.py
src/adapters/sqlite.py
src/api/__init__.py
src/api/api.py
src/api/middlewares.py
src/api/models.py
src/db/__init__.py
src/db/async_db.py
src/db/transactional.py
src/domain/__init__.py
src/domain/evaluation.py
src/domain/graph.py
src/domain/types.py
src/ensure/__init__.py
src/ensure/display.py
src/ensure/runner.py
src/ensure/validator.py
src/eval/__init__.py
src/eval/eval.py
src/events/__init__.py
src/events/handlers.py
src/events/models.py
src/execution/__init__.py
src/execution/js_eval.py
src/execution/python_eval.py
src/loaders/__init__.py
src/loaders/yaml_loader.py
src/migrations/README
src/migrations/__init__.py
src/migrations/env.py
src/migrations/script.py.mako
src/migrations/versions/18001fbb959a_add_postgres_support_with_jsonb_and_.py
src/migrations/versions/89ab3b24b597_initial_migration.py
src/secrets_manager/__init__.py
src/secrets_manager/secrets.py
src/sync/__init__.py
src/sync/checker.py
src/triggers/__init__.py
src/triggers/executor.py
src/utils/__init__.py
src/utils/sort.py
src/utils/text.py
src/utils/time.py
business_use_core-0.5.0.dist-info/METADATA
business_use_core-0.5.0.dist-info/WHEEL
business_use_core-0.5.0.dist-info/entry_points.txt
business_use_core-0.5.0.dist-info/licenses/LICENSE
business_use_core-0.5.0.dist-info/RECORD
