Metadata-Version: 2.4
Name: business-use-core
Version: 0.5.0
Summary: Business-Use Core CLI
Project-URL: Homepage, https://github.com/desplega-ai/business-use
Project-URL: Documentation, https://github.com/desplega-ai/business-use#readme
Project-URL: Repository, https://github.com/desplega-ai/business-use
Project-URL: Issues, https://github.com/desplega-ai/business-use/issues
Project-URL: Changelog, https://github.com/desplega-ai/business-use/releases
Author-email: Desplega AI <contact@desplega.ai>
Maintainer-email: Desplega AI <contact@desplega.ai>
License: MIT
License-File: LICENSE
Keywords: automation,event-driven,testing,workflow
Classifier: Development Status :: 3 - Alpha
Classifier: Intended Audience :: Developers
Classifier: License :: OSI Approved :: MIT License
Classifier: Programming Language :: Python :: 3
Classifier: Programming Language :: Python :: 3.12
Classifier: Programming Language :: Python :: 3.13
Classifier: Programming Language :: Python :: 3.14
Classifier: Topic :: Software Development :: Libraries :: Python Modules
Classifier: Topic :: Software Development :: Testing
Requires-Python: >=3.12
Requires-Dist: aiosqlite>=0.20.0
Requires-Dist: alembic>=1.15.0
Requires-Dist: asyncpg>=0.30.0
Requires-Dist: bubus>=1.5.6
Requires-Dist: click>=8.1.0
Requires-Dist: fastapi[standard]>=0.119.1
Requires-Dist: greenlet>=3.0.0
Requires-Dist: httpx>=0.27.0
Requires-Dist: pydantic>=2.12.3
Requires-Dist: pyyaml>=6.0.0
Requires-Dist: questionary>=2.1.0
Requires-Dist: quickjs>=1.19.2
Requires-Dist: sqlmodel>=0.0.27
Requires-Dist: uuid>=1.30
